thutil/__init__.py
thutil/_version.py
thutil/config.py
thutil/io.py
thutil/jobman.py
thutil/path.py
thutil/pkg.py
thutil/sth2sth.py
thutil/stuff.py
thutil/schema/example_machine_config.yml
thutil/schema/schema_arg_remote_machine.yml
thutil-25.5.22.dist-info/licenses/LICENSE.md
thutil-25.5.22.dist-info/METADATA
thutil-25.5.22.dist-info/WHEEL
thutil-25.5.22.dist-info/top_level.txt
thutil-25.5.22.dist-info/RECORD
