Metadata-Version: 2.4
Name: thutil
Version: 25.5.22
Summary: The Python package of general ulitities.
Author-email: "C.Thang Nguyen" <thangckt@gmail.com>
License: MIT License
Requires-Python: >=3.9
License-File: LICENSE.md
Requires-Dist: pyyaml
Requires-Dist: requests
Requires-Dist: cerberus
Requires-Dist: omegaconf
Requires-Dist: dpdispatcher
Provides-Extra: test
Requires-Dist: pytest; extra == "test"
Requires-Dist: pytest-cov; extra == "test"
Dynamic: license-file
